rtl/moola_dp_sram.sv
//=============================================================================
// IP Name      : Moola True Dual-Port Byte-Enable SRAM (moola_dp_sram)
// Description  : Parameterized, FPGA-BRAM inferable True Dual-Port Synchronous
//                SRAM with independent byte write strobes per port.
// Features     : 
//   - Fully parameterizable DATA_WIDTH, ADDR_WIDTH, and BYTE_WIDTH
//   - Independent Clock, Enable, Write-Strobe, Address, and Data buses per port
//   - True Read-First synchronous memory array behavior
//   - Clean 32-bit word Hex memory initialization ($readmemh) support
//=============================================================================

`timescale 1ns / 1ps

module moola_dp_sram #(
  parameter int DATA_WIDTH     = 32,                          // Width of data bus in bits
  parameter int ADDR_WIDTH     = 14,                          // Depth = 2^ADDR_WIDTH (14 = 16384 words = 64 KB for 32-bit)
  parameter int BYTE_WIDTH     = 8,                           // Bits per byte lane
  parameter int NUM_BYTES      = DATA_WIDTH / BYTE_WIDTH,     // Number of byte strobes
  parameter bit INIT_FILE_EN   = 1'b0,                        // Enable pre-loading from file
  parameter string INIT_FILE   = "mem_init.hex"               // Path to hex file
)(
  // -------------------------------------------------------------------------
  // Port A Interface (Typically Instruction Fetch / IMEM)
  // -------------------------------------------------------------------------
  input  logic                      clk_a,
  input  logic                      rst_a,                    // Synchronous read-port reset
  input  logic                      en_a,                     // Port A chip enable
  input  logic [NUM_BYTES-1:0]      wstrb_a,                  // Port A byte-write enable mask
  input  logic [ADDR_WIDTH-1:0]     addr_a,                   // Port A word address
  input  logic [DATA_WIDTH-1:0]     wdata_a,                  // Port A write data
  output logic [DATA_WIDTH-1:0]     rdata_a,                  // Port A read data (registered output)

  // -------------------------------------------------------------------------
  // Port B Interface (Typically Data Load/Store / DMEM)
  // -------------------------------------------------------------------------
  input  logic                      clk_b,
  input  logic                      rst_b,                    // Synchronous read-port reset
  input  logic                      en_b,                     // Port B chip enable
  input  logic [NUM_BYTES-1:0]      wstrb_b,                  // Port B byte-write enable mask
  input  logic [ADDR_WIDTH-1:0]     addr_b,                   // Port B word address
  input  logic [DATA_WIDTH-1:0]     wdata_b,                  // Port B write data
  output logic [DATA_WIDTH-1:0]     rdata_b                   // Port B read data (registered output)
);

  // -------------------------------------------------------------------------
  // Parameter Validation
  // -------------------------------------------------------------------------
  initial begin
    if (DATA_WIDTH % BYTE_WIDTH != 0) begin
      $fatal(1, "[moola_tdp_sram] DATA_WIDTH (%0d) must be an integer multiple of BYTE_WIDTH (%0d).",
             DATA_WIDTH, BYTE_WIDTH);
    end
  end

  // Derive total memory depth in words
  localparam int DEPTH = 1 << ADDR_WIDTH;

  // -------------------------------------------------------------------------
  // Memory Array Definition
  // -------------------------------------------------------------------------
  // 2D byte-split array guarantees clean FPGA BRAM write-strobe inference
  (* ram_style = "block" *) logic [BYTE_WIDTH-1:0] mem_array [NUM_BYTES-1:0][DEPTH-1:0];

  // Internal output registers for synchronous read latency (1 cycle)
  logic [DATA_WIDTH-1:0] rdata_a_reg;
  logic [DATA_WIDTH-1:0] rdata_b_reg;

  // -------------------------------------------------------------------------
  // Memory Array Initialization
  // -------------------------------------------------------------------------
  initial begin
    // Clear entire memory array to zero
    for (int b = 0; b < NUM_BYTES; b++) begin
      for (int w = 0; w < DEPTH; w++) begin
        mem_array[b][w] = '0;
      end
    end

    // Pre-load from hex file if enabled
    if (INIT_FILE_EN) begin
      logic [DATA_WIDTH-1:0] temp_mem [DEPTH-1:0];
      
      // Initialize temp_mem to zero so unwritten hex lines don't become 'X'
      for (int w = 0; w < DEPTH; w++) begin
        temp_mem[w] = '0;
      end

      $display("[moola_dp_sram] Preloading memory data from: %s", INIT_FILE);
      $readmemh(INIT_FILE, temp_mem);

      // Distribute 32-bit words into individual byte slices
      for (int w = 0; w < DEPTH; w++) begin
        for (int b = 0; b < NUM_BYTES; b++) begin
          mem_array[b][w] = temp_mem[w][(b*BYTE_WIDTH) +: BYTE_WIDTH];
        end
      end
    end
  end

  // -------------------------------------------------------------------------
  // Port A Synchronous Logic (Read-First Mode)
  // -------------------------------------------------------------------------
  generate
    for (genvar i = 0; i < NUM_BYTES; i++) begin : gen_port_a
      always_ff @(posedge clk_a) begin
        if (rst_a) begin
          rdata_a_reg[(i*BYTE_WIDTH) +: BYTE_WIDTH] <= '0;
        end else if (en_a) begin
          // Synchronous Read: latches data currently in the array
          rdata_a_reg[(i*BYTE_WIDTH) +: BYTE_WIDTH] <= mem_array[i][addr_a];

          // Synchronous Byte Write: updates byte lane if strobe bit is high
          if (wstrb_a[i]) begin
            mem_array[i][addr_a] <= wdata_a[(i*BYTE_WIDTH) +: BYTE_WIDTH];
          end
        end
      end
    end
  endgenerate

  // -------------------------------------------------------------------------
  // Port B Synchronous Logic (Read-First Mode)
  // -------------------------------------------------------------------------
  generate
    for (genvar j = 0; j < NUM_BYTES; j++) begin : gen_port_b
      always_ff @(posedge clk_b) begin
        if (rst_b) begin
          rdata_b_reg[(j*BYTE_WIDTH) +: BYTE_WIDTH] <= '0;
        end else if (en_b) begin
          // Synchronous Read: latches data currently in the array
          rdata_b_reg[(j*BYTE_WIDTH) +: BYTE_WIDTH] <= mem_array[j][addr_b];

          // Synchronous Byte Write: updates byte lane if strobe bit is high
          if (wstrb_b[j]) begin
            mem_array[j][addr_b] <= wdata_b[(j*BYTE_WIDTH) +: BYTE_WIDTH];
          end
        end
      end
    end
  endgenerate

  // Continuous assignments to drive output ports
  assign rdata_a = rdata_a_reg;
  assign rdata_b = rdata_b_reg;

endmodule : moola_dp_sram

tb/tb_moola_dp_sram.sv
//=============================================================================
// Testbench : tb_moola_dp_sram
// Purpose   : Comprehensive self-checking verification testbench for 
//             moola_dp_sram IP core.
// Tests     :
//   1. Hex preload verification on Port A and Port B
//   2. Byte-masked writes on Port A (testing individual byte strobes)
//   3. Concurrent dual-port operations (Port A Write -> Port B Read)
//   4. Synchronous reset validation
//=============================================================================

`timescale 1ns / 1ps

module tb_moola_dp_sram;

  localparam int DATA_WIDTH = 32;
  localparam int ADDR_WIDTH = 10; // 1024 words depth for simulation speed
  localparam int BYTE_WIDTH = 8;
  localparam int NUM_BYTES  = DATA_WIDTH / BYTE_WIDTH;

  // Port A Signals
  logic                  clk_a;
  logic                  rst_a;
  logic                  en_a;
  logic [NUM_BYTES-1:0]  wstrb_a;
  logic [ADDR_WIDTH-1:0] addr_a;
  logic [DATA_WIDTH-1:0] wdata_a;
  logic [DATA_WIDTH-1:0] rdata_a;

  // Port B Signals
  logic                  clk_b;
  logic                  rst_b;
  logic                  en_b;
  logic [NUM_BYTES-1:0]  wstrb_b;
  logic [ADDR_WIDTH-1:0] addr_b;
  logic [DATA_WIDTH-1:0] wdata_b;
  logic [DATA_WIDTH-1:0] rdata_b;

  // Verification Error Tracking
  int error_count = 0;

  // -------------------------------------------------------------------------
  // Device Under Test (DUT) Instantiation
  // -------------------------------------------------------------------------
  moola_dp_sram #(
    .DATA_WIDTH   (DATA_WIDTH),
    .ADDR_WIDTH   (ADDR_WIDTH),
    .BYTE_WIDTH   (BYTE_WIDTH),
    .INIT_FILE_EN (1'b1),
    .INIT_FILE    ("tb/mem_test.hex")
  ) dut (
    .clk_a   (clk_a),
    .rst_a   (rst_a),
    .en_a    (en_a),
    .wstrb_a (wstrb_a),
    .addr_a  (addr_a),
    .wdata_a (wdata_a),
    .rdata_a (rdata_a),

    .clk_b   (clk_b),
    .rst_b   (rst_b),
    .en_b    (en_b),
    .wstrb_b (wstrb_b),
    .addr_b  (addr_b),
    .wdata_b (wdata_b),
    .rdata_b (rdata_b)
  );

  // -------------------------------------------------------------------------
  // Clocks: Dual independent clock domains
  // -------------------------------------------------------------------------
  initial clk_a = 0;
  always #5.0 clk_a = ~clk_a; // 100 MHz

  initial clk_b = 0;
  always #3.7 clk_b = ~clk_b; // ~135 MHz (Asynchronous relationship)

  // -------------------------------------------------------------------------
  // Waveform Dump Setup
  // -------------------------------------------------------------------------
  initial begin
    $dumpfile("sim/tb_moola_dp_sram.vcd");
    $dumpvars(0, tb_moola_dp_sram);
  end

  // Helper check task
  task check(string test_name, logic [DATA_WIDTH-1:0] actual, logic [DATA_WIDTH-1:0] expected);
    if (actual !== expected) begin
      $display("[FAIL] %-35s | Expected: 0x%08h | Got: 0x%08h at %0t ps", test_name, expected, actual, $time);
      error_count++;
    end else begin
      $display("[PASS] %-35s | Actual: 0x%08h", test_name, actual);
    end
  endtask

  // -------------------------------------------------------------------------
  // Main Verification Routine
  // -------------------------------------------------------------------------
  initial begin
    $display("\n========================================================");
    $display("   STARTING MOOLA DUAL-PORT SRAM IP VERIFICATION        ");
    $display("========================================================\n");

    // Initialize all input ports
    rst_a   = 1'b1;
    en_a    = 1'b0;
    wstrb_a = '0;
    addr_a  = '0;
    wdata_a = '0;

    rst_b   = 1'b1;
    en_b    = 1'b0;
    wstrb_b = '0;
    addr_b  = '0;
    wdata_b = '0;

    // Apply synchronous reset for 2 cycles
    @(posedge clk_a);
    @(posedge clk_a);
    rst_a = 1'b0;
    rst_b = 1'b0;
    en_a  = 1'b1;
    en_b  = 1'b1;

    // -----------------------------------------------------------------------
    // TEST 1: Hex Preload Verification on Both Ports
    // -----------------------------------------------------------------------
    $display("[TEST 1] Verifying Hex Preloading on Port A and Port B...");
    addr_a = 10'h000; // Expected: 0x11223344
    addr_b = 10'h001; // Expected: 0x55667788

    @(posedge clk_a);
    #1;
    check("Port A Read Word 0", rdata_a, 32'h11223344);

    @(posedge clk_b);
    #1;
    check("Port B Read Word 1", rdata_b, 32'h55667788);

    // -----------------------------------------------------------------------
    // TEST 2: Byte-Masked Writes on Port A
    // -----------------------------------------------------------------------
    $display("\n[TEST 2] Verifying Byte-Strobe Writes on Port A...");
    // Step A: Write Byte 0 (0xBB) and Byte 2 (0xAA) to word address 0x010
    @(posedge clk_a);
    addr_a  <= 10'h010;
    wdata_a <= 32'h00AA_00BB;
    wstrb_a <= 4'b0101; // Enable byte 2 and byte 0

    // Step B: Write Byte 1 (0xDD) and Byte 3 (0xCC) to same word address 0x010
    @(posedge clk_a);
    wdata_a <= 32'hCC00_DD00;
    wstrb_a <= 4'b1010; // Enable byte 3 and byte 1

    // Step C: Read back the assembled 32-bit word
    @(posedge clk_a);
    wstrb_a <= 4'b0000;
    
    @(posedge clk_a);
    #1;
    check("Port A Byte-Strobe Reassembly", rdata_a, 32'hCCAA_DDBB);

    // -----------------------------------------------------------------------
    // TEST 3: Concurrent Operations (Port A Write -> Port B Read)
    // -----------------------------------------------------------------------
    $display("\n[TEST 3] Verifying Cross-Port Concurrency (Write A -> Read B)...");
    @(posedge clk_a);
    addr_a  <= 10'h025;
    wdata_a <= 32'hDEAD_BEEF;
    wstrb_a <= 4'b1111; // Full word write
    
    @(posedge clk_a);
    wstrb_a <= 4'b0000;

    // Read that same address from Port B synchronously
    @(posedge clk_b);
    addr_b <= 10'h025;
    
    @(posedge clk_b);
    #1;
    check("Port B Cross-Port Read", rdata_b, 32'hDEAD_BEEF);

    // -----------------------------------------------------------------------
    // Final Summary
    // -----------------------------------------------------------------------
    $display("\n========================================================");
    if (error_count == 0) begin
      $display("   ALL DUAL-PORT SRAM TESTS PASSED SUCCESSFULLY!       ");
    end else begin
      $display("   VERIFICATION FAILED: %0d ERROR(S) ENCOUNTERED.      ", error_count);
    end
    $display("========================================================\n");

    $finish;
  end

endmodule : tb_moola_dp_sram

sim/tb_moola_dp_sram.vcd
$date
	Tue Sep  1 17:19:58 2026
$end
$version
	Icarus Verilog
$end
$timescale
	1ps
$end
$scope module tb_moola_dp_sram $end
$var wire 32 ! rdata_b [31:0] $end
$var wire 32 " rdata_a [31:0] $end
$var parameter 32 # ADDR_WIDTH $end
$var parameter 32 $ BYTE_WIDTH $end
$var parameter 32 % DATA_WIDTH $end
$var parameter 32 & NUM_BYTES $end
$var reg 10 ' addr_a [9:0] $end
$var reg 10 ( addr_b [9:0] $end
$var reg 1 ) clk_a $end
$var reg 1 * clk_b $end
$var reg 1 + en_a $end
$var reg 1 , en_b $end
$var reg 1 - rst_a $end
$var reg 1 . rst_b $end
$var reg 32 / wdata_a [31:0] $end
$var reg 32 0 wdata_b [31:0] $end
$var reg 4 1 wstrb_a [3:0] $end
$var reg 4 2 wstrb_b [3:0] $end
$var integer 32 3 error_count [31:0] $end
$scope module dut $end
$var wire 10 4 addr_a [9:0] $end
$var wire 10 5 addr_b [9:0] $end
$var wire 1 ) clk_a $end
$var wire 1 * clk_b $end
$var wire 1 + en_a $end
$var wire 1 , en_b $end
$var wire 32 6 rdata_a [31:0] $end
$var wire 32 7 rdata_b [31:0] $end
$var wire 1 - rst_a $end
$var wire 1 . rst_b $end
$var wire 32 8 wdata_a [31:0] $end
$var wire 32 9 wdata_b [31:0] $end
$var wire 4 : wstrb_a [3:0] $end
$var wire 4 ; wstrb_b [3:0] $end
$var parameter 32 < ADDR_WIDTH $end
$var parameter 32 = BYTE_WIDTH $end
$var parameter 32 > DATA_WIDTH $end
$var parameter 32 ? DEPTH $end
$var parameter 120 @ INIT_FILE $end
$var parameter 1 A INIT_FILE_EN $end
$var parameter 32 B NUM_BYTES $end
$var reg 32 C rdata_a_reg [31:0] $end
$var reg 32 D rdata_b_reg [31:0] $end
$scope begin gen_port_a[0] $end
$var parameter 2 E i $end
$upscope $end
$scope begin gen_port_a[1] $end
$var parameter 2 F i $end
$upscope $end
$scope begin gen_port_a[2] $end
$var parameter 3 G i $end
$upscope $end
$scope begin gen_port_a[3] $end
$var parameter 3 H i $end
$upscope $end
$scope begin gen_port_b[0] $end
$var parameter 2 I j $end
$upscope $end
$scope begin gen_port_b[1] $end
$var parameter 2 J j $end
$upscope $end
$scope begin gen_port_b[2] $end
$var parameter 3 K j $end
$upscope $end
$scope begin gen_port_b[3] $end
$var parameter 3 L j $end
$upscope $end
$scope begin $ivl_for_loop0 $end
$var integer 32 M b [31:0] $end
$scope begin $ivl_for_loop1 $end
$var integer 32 N w [31:0] $end
$upscope $end
$upscope $end
$scope begin $unm_blk_6 $end
$scope begin $ivl_for_loop2 $end
$var integer 32 O w [31:0] $end
$upscope $end
$scope begin $ivl_for_loop3 $end
$var integer 32 P w [31:0] $end
$scope begin $ivl_for_loop4 $end
$var integer 32 Q b [31:0] $end
$upscope $end
$upscope $end
$upscope $end
$upscope $end
$scope task check $end
$var reg 32 R actual [31:0] $end
$var reg 32 S expected [31:0] $end
$upscope $end
$upscope $end
$enddefinitions $end
$comment Show the parameter values. $end
$dumpall
b11 L
b10 K
b1 J
b0 I
b11 H
b10 G
b1 F
b0 E
b100 B
1A
b11101000110001000101111011011010110010101101101010111110111010001100101011100110111010000101110011010000110010101111000 @
b10000000000 ?
b100000 >
b1000 =
b1010 <
b100 &
b100000 %
b1000 $
b1010 #
$end
#0
$dumpvars
bx S
bx R
b100 Q
b10000000000 P
b10000000000 O
b10000000000 N
b100 M
bx D
bx C
b0 ;
b0 :
b0 9
b0 8
bx 7
bx 6
b0 5
b0 4
b0 3
b0 2
b0 1
b0 0
b0 /
1.
1-
0,
0+
0*
0)
b0 (
b0 '
bx "
bx !
$end
#3700
b0 !
b0 7
b0 D
1*
#5000
b0 "
b0 6
b0 C
1)
#7400
0*
#10000
0)
#11100
1*
#14800
0*
#15000
b1 (
b1 5
1,
1+
0.
0-
1)
#18500
b1010101011001100111011110001000 !
b1010101011001100111011110001000 7
b1010101011001100111011110001000 D
1*
#20000
0)
#22200
0*
#25000
b10001001000100011001101000100 "
b10001001000100011001101000100 6
b10001001000100011001101000100 C
1)
#25900
1*
#26000
b10001001000100011001101000100 S
b10001001000100011001101000100 R
#29600
0*
#30000
0)
#33300
1*
#34300
b1010101011001100111011110001000 S
b1010101011001100111011110001000 R
#35000
b101 1
b101 :
b101010100000000010111011 /
b101010100000000010111011 8
b10000 '
b10000 4
1)
#37000
0*
#40000
0)
#40700
1*
#44400
0*
#45000
b1010 1
b1010 :
b11001100000000001101110100000000 /
b11001100000000001101110100000000 8
b0 "
b0 6
b0 C
1)
#48100
1*
#50000
0)
#51800
0*
#55000
b101010100000000010111011 "
b101010100000000010111011 6
b101010100000000010111011 C
b0 1
b0 :
1)
#55500
1*
#59200
0*
#60000
0)
#62900
1*
#65000
b11001100101010101101110110111011 "
b11001100101010101101110110111011 6
b11001100101010101101110110111011 C
1)
#66000
b11001100101010101101110110111011 S
b11001100101010101101110110111011 R
#66600
0*
#70000
0)
#70300
1*
#74000
0*
#75000
b1111 1
b1111 :
b11011110101011011011111011101111 /
b11011110101011011011111011101111 8
b100101 '
b100101 4
1)
#77700
1*
#80000
0)
#81400
0*
#85000
b0 1
b0 :
b0 "
b0 6
b0 C
1)
#85100
b100101 (
b100101 5
1*
#88800
0*
#90000
0)
#92500
b11011110101011011011111011101111 !
b11011110101011011011111011101111 7
b11011110101011011011111011101111 D
1*
#93500
b11011110101011011011111011101111 S
b11011110101011011011111011101111 R
